README.rst
setup.cfg
setup.py
scluster/__init__.py
scluster/clusterer.py
scluster/evaluate.py
scluster.egg-info/PKG-INFO
scluster.egg-info/SOURCES.txt
scluster.egg-info/dependency_links.txt
scluster.egg-info/pbr.json
scluster.egg-info/requires.txt
scluster.egg-info/top_level.txt
tests/__init__.py
tests/scluster_tests.py