Metadata-Version: 1.0
Name: scluster
Version: 0.0.1
Summary: an implementation of spectral clustering for text document collections
Home-page: https://github.com/whym/scluster
Author: Yusuke Matsubara
Author-email: whym@whym.org
License: MIT
Platform: UNKNOWN
